{"data_mtime": 1593013663, "dep_lines": [3, 6, 1, 1, 1, 1, 2, 4, 5, 7, 8], "dep_prios": [5, 5, 5, 30, 30, 5, 5, 5, 5, 5, 5], "dependencies": ["Books.models", "Books.forms", "builtins", "abc", "typing"], "hash": "4d0547ed98412684bba31a787a87f15b6d0a84f25a5251358590e11f73ca8c67", "id": "Books.views", "ignore_all": false, "interface_hash": "5d6d75d23b5801ff2098917cc4ac0cf2aca7b7320194e306f0997604c96f2424", "mtime": 1587099325, "options": {"allow_redefinition": false, "allow_untyped_globals": false, "always_false": [], "always_true": [], "bazel": false, "check_untyped_defs": false, "disallow_any_decorated": false, "disallow_any_explicit": false, "disallow_any_expr": false, "disallow_any_generics": false, "disallow_any_unimported": false, "disallow_incomplete_defs": false, "disallow_subclassing_any": false, "disallow_untyped_calls": false, "disallow_untyped_decorators": false, "disallow_untyped_defs": false, "follow_imports": "silent", "follow_imports_for_stubs": false, "ignore_errors": false, "ignore_missing_imports": true, "implicit_reexport": true, "local_partial_types": false, "mypyc": false, "no_implicit_optional": false, "platform": "win32", "plugins": [], "show_none_errors": true, "strict_equality": false, "strict_optional": true, "strict_optional_whitelist": null, "warn_no_return": true, "warn_return_any": false, "warn_unreachable": false, "warn_unused_ignores": false}, "path": "d:\\Pyhon Django\\SellingCart\\Books\\views.py", "plugin_data": null, "size": 1243, "suppressed": ["django.shortcuts", "django.http", "django", "django.core.files.storage", "django.contrib.auth.decorators", "django.db.models"], "version_id": "0.770"}